Workbook
Name __bookmark_1: CH_CA Charge [1]Master!$A$2:$AT$12030

Sheet Top 50 List
A1: Count | B1: Description | C1: Procedure Type
A2: 210 | B2: X-Ray, Chest, two views | C2: Radiology - X-Ray
A3: 201 | B3: Electrocardiogram | C3: Medicine - Cardiovascular
A4: 167 | B4: Comprehensive Metabolic Panel | C4: Laboratory
A5: 148 | B5: Complete Blood Count, with differential | C5: Laboratory
A6: 142 | B6: Basic Metabolic Panel | C6: Laboratory
A7: 134 | B7: X-Ray, Chest, one view | C7: Radiology - X-Ray
A8: 127 | B8: Prothrombin Time | C8: Laboratory
A9: 127 | B9: Physical Therapy - Therapeutic Exercise | C9: Medicine - Physical Medicine
A10: 121 | B10: Mammography, Screening, Bilateral | C10: Radiology
A11: 119 | B11: Colonoscopy | C11: Surgery
A12: 116 | B12: CT Scan, Head or Brain, without contrast | C12: Radiology - CT Scan
A13: 114 | B13: Urinalysis | C13: Laboratory
... A51: 34 | B51: Culture, Urine | C51: Laboratory

Sheet AB 1045 Form
A1: Hospital Name: Chinese Hospital
A2: HCAI Facility No: 106382715
A3: Effective Date of Charges: 06/01/2024
A4: In response to requests from hospitals and the public, HCAI has developed this form to assist hospitals in collecting and submitting the average charge for 25 common outpatient procedures performed by hospitals, as required by AB 1045 (Chapter 532, Statutes of 2005). Use of the HCAI form is voluntary, but highly encouraged, as it allows hospitals to report and the public to compare uniform information regarding common outpatient procedures.
A5: Evaluation & Management Services (CPT Codes 99201-99499) | B5: 2024 CPT Code | C5: Average Charge
A6: Emergency Room Visit (straightforward) | B6: 99282 | C6: 695
A7: Emergency Room Visit (low level) | B7: 99283 | C7: 1300
A8: Emergency Room Visit (moderate level) | B8: 99284 | C8: 2043
A9: Emergency Room Visit (high level) | B9: 99285 | C9: 2928
A10: Outpatient Visit, established patient, 20+ minutes | B10: 99213 | C10: 171
A11: Laboratory & Pathology Services (CPT Codes 80047-89398) | B11: 2024 CPT Code | C11: Average Charge
A12: Basic Metabolic Panel | B12: 80048 | C12: 120
A13: Blood Gas Analysis, including 02 saturation | B13: 82805
A14: Complete Blood Count, automated | B14: 85027 | C14: 194
A15: Complete Blood Count, with differential WBC, automated | B15: 85025 | C15: 194
A16: Comprehensive Metabolic Panel | B16: 80053 | C16: 344
A17: Creatine Kinase (CK), (CPK), Total | B17: 82550 | C17: 227
A18: Lipid Panel | B18: 80061 | C18: 218
A19: Partial Thromboplastin Time | B19: 85730 | C19: 235
A20: Prothrombin Time | B20: 85610 | C20: 213
A21: Thyroid Stimulating Hormone | B21: 84443 | C21: 308
A22: Troponin, Quantitative | B22: 84484 | C22: 204
A23: Urinalysis, without microscopy | B23: 81002 or 81003 | C23: 26
A24: Urinalysis, with microscopy | B24: 81000 or 81001 | C24: 166
A25: Radiology Services (CPT Codes 70010-79999) | B25: 2024 CPT Code | C25: Average Charge
A26: CT Scan, Abdomen, with contrast | B26: 74160 | C26: 3275
A27: CT Scan, Head or Brain, without contrast | B27: 70450 | C27: 2480
A28: CT Scan, Pelvis, with contrast | B28: 72193
A29: Mammography, Screening, Bilateral | B29: 77067 | C29: 516
A30: MRI, Brain, without contrast, followed by contrast | B30: 70553 | C30: 6300
A31: Ultrasound, Abdomen, Complete | B31: 76700 | C31: 2103
A32: Ultrasound, OB, 14 weeks or more, transabdominal | B32: 76805
A33: X-Ray, Lower Back, minimum four views | B33: 72110 | C33: 974
A34: X-Ray, Chest, two views | B34: 71046 | C34: 566
A35: Medicine Services (CPT Codes 90281-99607) | B35: 2024 CPT Code | C35: Average Charge
A36: Cardiac Catheterization, Left Heart, percutaneous | B36: 93452
A37: Echocardiography, Transthoracic, complete, without Doppler | B37: 93307 | C37: 591
A38: Electrocardiogram, routine, with interpretation and report | B38: 93000 | C38: 79
A39: Inhalation Treatment, pressurized or nonpressurized | B39: 94640 | C39: 1042
A40: Physical Therapy, Evaluation | B40: 97161-97163 | C40: 553
A41: Physical Therapy, Gait Training | B41: 97116 | C41: 286
A42: Physical Therapy, Therapeutic Exercise | B42: 97110 | C42: 286
A43: Surgery Services (CPT Codes 10021-69990) | B43: 2024 CPT Code | C43: Average Charge
A44: Arthroscopy, Knee, with meniscectomy (medial or lateral) | B44: 29881
A45: Arthroscopy, Shoulder, with partial acromioplasty | B45: 29826
A46: Carpal Tunnel Surgery | B46: 64721
A47: Cataract Removal with Insertion of Intraocular Lens, 1 Stage | B47: 66984
A48: Colonoscopy, diagnostic | B48: 45378 | C48: 4047
A49: Colonoscopy, with biopsy | B49: 45380 | C49: 6984
A50: Colonoscopy, with lesion removal, by snare technique | B50: 45385 | C50: 5723
A51: Discission, secondary membranous cataract, laser surgery | B51: 66821 | C51: 6388
A52: Endoscopy, Upper GI, with biopsy | B52: 43239 | C52: 6388
A53: Endoscopy, Upper GI, diagnostic | B53: 43235 | C53: 6388
A54: Excision, Breast Lesion, without preoperative radiological marker | B54: 19120
A55: Hernia Repair, Inguinal, 5 years and older | B55: 49505
A56: Injection, Diagnostic or Therapeutic substance, epidural, lumbar | B56: 62322-62323
A57: Injection, Anesthetic or Steroid, transforaminal epidural, lumbar | B57: 64483
A58: Laparoscopic Cholecystectomy | B58: 47562
A59: Tympanostomy (insert ventilating tube, general anesthesia) | B59: 69436
A60: Tonsillectomy with Adenoidectomy, less than 12 years old | B60: 42820
A61: Other Common Outpatient Procedures (list as needed) | B61: 2024 CPT Code | C61: Average Charge
A72: Count of Reported Procedures (minimum 25 required) | C72: =COUNTA(C6:C10,C12:C24,C26:C34,C36:C42,C44:C60,C62:C71) -> 36
A73: Instructions for Completing AB 1045 Common Outpatient Procedure Form
A74: 1. Enter Hospital Name and HCAI Facility Number. Revise Effective Date of Charges, if necessary.
A75: 2. Enter Average Charge for at least 25 commonly performed outpatient procedures. For Evaluation & Management
A76: Services, do not include related ancillary charges. For all other procedures, include related ancillary charges.
A77: NOTE: The CPT codes are included on this form to help identify the listed procedures based on the frequencies
A78: across hospital-based ambulatory surgery data. The average charge for all related services and procedures
A79: (e.g., supplies, drugs, lab, use of operating room, etc.) should be included in the average charge for that procedure.
A80: 3. Do not change procedure descriptions or CPT code references. Use "Other Common Outpatient Procedures"
A81: (rows 62-71) if you are unable to select procedures from list.
A82: 4. Submit completed form as Excel (.xls) file, along with chargemaster and percent change in gross revenue
A83: calculation, by e-mail to chargemaster@hcai.ca.gov or by standard mail on CD.

Sheet CDM
A1: BillItemId | B1: BillItemLongDesc | C1: Charge
A2: 675856 | B2: BiPAP Management | C2: 0
A3: 675861 | B3: Bi-level Positive Airway Pressure | C3: 0
A4: 675862 | B4: Bi-level Positive Airway Pressure | C4: 0
A5: 758747 | B5: Local | C5: 0
A6: 758750 | B6: Regional Block | C6: 0
A7: 758754 | B7: General | C7: 0
A8: 758755 | B8: MAC | C8: 0
A9: 758757 | B9: Minor | C9: 0
A10: 884755 | B10: Moderate Sedation | C10: 0
A11: 958641 | B11: Alk Phos Isoenzyme LC | C11: 0
A12: 990676 | B12: ROOM/BED: Observation | C12: 0
A13: 1211602 | B13: .Gram Stain RLC | C13: 0
... A807: 50778191 | B807: Sodium Chloride 0.45% IV Sol 500 mL [CHA] | C807: 0
A808: 50792963 | B808: 81405 | C808: 0
A809: 50792964 | B809: 81406 | C809: 0
A810: 50792965 | B810: 82784 | C810: 0
A811: 50792966 | B811: 83516 | C811: 0
A812: 50792967 | B812: 83520 | C812: 0
A813: 50792968 | B813: 83883 | C813: 0
A814: 50792969 | B814: 86003 | C814: 0
A815: 50792970 | B815: 86008 | C815: 0
A816: 50792971 | B816: 86146 | C816: 0
A817: 50792972 | B817: 86147 | C817: 0
A818: 50792973 | B818: 86148 | C818: 0
A819: 50792974 | B819: 86160 | C819: 0
... A830: 50792985 | B830: 88185 | C830: 0
A831: 50866740 | B831: .6-Acetylmorphine Rescreen LC | C831: 0
A832: 50866742 | B832: .AMP/MAMP ReScreen, Urine LC | C832: 0
A833: 50866747 | B833: .Cocaine Metabolite ReScreen, U LC | C833: 0
A834: 50866749 | B834: .Codeine/Morphine Rescreen, Ur LC | C834: 0
A835: 50866754 | B835: .HYC/HYM ReScreen, Urine LC | C835: 0
A836: 50866758 | B836: .Opiates Conf Ur 799437 LC | C836: 0
A837: 50866760 | B837: .OXYC/OXYM ReScreen, Urine LC | C837: 0
A838: 50866762 | B838: .PCP Rescreen, Urine LC | C838: 0
A839: 50866765 | B839: .THCA ReScreen, Urine LC | C839: 0
A840: 50866768 | B840: Pap IG Aptima HPV,CtNg Age Gdln (Chart) LC | C840: 0
A841: 50878576 | B841: 80359 | C841: 0
A842: 50878577 | B842: 80361 | C842: 0
A843: 50878578 | B843: 82247 | C843: 0
A844: 50878579 | B844: 82248 | C844: 0
A845: 50878580 | B845: 82310 | C845: 0
A846: 50878581 | B846: 82435 | C846: 0
A847: 50878582 | B847: 82565 | C847: 0
A848: 50878583 | B848: 82570 | C848: 0
A849: 50878585 | B849: 82652 | C849: 0
A850: 50878586 | B850: 82746 | C850: 0
A851: 50878587 | B851: 82947 | C851: 0
A852: 50878588 | B852: 83002 | C852: 0
... A877: 50878615 | B877: 89060 | C877: 0
A878: 50903928 | B878: Blood component or product not otherwise classified | C878: 0
A879: 50974627 | B879: Dextrose 5% with 0.225% NaCl IV Sol 1000 mL [CHA] | C879: 0
A880: 51007649 | B880: Dextrose 5% with 0.225% NaCl IV Sol 1000 mL [CHA] | C880: 0
A881: 51029084 | B881: Dextrose 5% with NS IV Sol 500 mL [CHA] | C881: 0
A882: 51042108 | B882: Dextrose 5% in Water IV Sol 500 mL non-PVC [CHA] | C882: 0
A883: 51042108 | B883: Dextrose 5% in Water IV Sol 500 mL non-PVC [CHA] | C883: 0
A884: 51496675 | B884: 87529-HSV 1/2 PCR LC | C884: 0
A885: 51496677 | B885: 82570-Copper, Urine LC | C885: 0
A886: 51539513 | B886: 84165 | C886: 0
A887: 51539514 | B887: 86334 | C887: 0
A888: 51539515 | B888: 83521 | C888: 0
A889: 51543193 | B889: J1010-Injection, methylprednisolone acetate, 1 mg | C889: 0
A890: 51550671 | B890: J1010 Injection, methylprednisolone acetate, 1 mg | C890: 0
A891: 51577731 | B891: 83516-(ANCA) Profile LC | C891: 0
A892: 51577732 | B892: 86037-ANCA Profile LC | C892: 0
A893: 17556858 | B893: CN 100% impaired | C893: 0.01
A894: 17556859 | B894: CM At least 80% but less than 100% impaired | C894: 0.01
A895: 17556860 | B895: CL At least 60% but less than 80% impaired | C895: 0.01
A896: 17556861 | B896: CK At least 40% but less than 60% impaired | C896: 0.01
A897: 17556862 | B897: CJ At least 20% but less than 40% impaired | C897: 0.01
A898: 17556863 | B898: CI At least 1% but less than 20% impaired | C898: 0.01
A899: 17556864 | B899: CH 0% impaired | C899: 0.01
A900: 17556865 | B900: CN 100% impaired | C900: 0.01
... A1461: 49312588 | B1461: BULB SYRINGE | C1461: 6
A1462: 49312595 | B1462: 4 | C1462: 6
A1463: 49555218 | B1463: SPLINT PLASTER 4X5IN TechFee | C1463: 6
A1464: 49582807 | B1464: STOPCOCK 3-WAY PORT COVERS LUER LOCK | C1464: 6
A1465: 49582936 | B1465: VASELINE PETROLATUM GAUZE 1" X 8" | C1465: 6
A1466: 49582938 | B1466: VASELINE GAUZE 1" X 8" DRESSING | C1466: 6
A1467: 49583159 | B1467: ET TUBE ADAPTOR (PLASTIC WHITE) | C1467: 6
A1468: 50071344 | B1468: Bacterial Identification and Susceptibility, Aerobic QST | C1468: 6
A1469: 50324556 | B1469: 60687-0242-01 - sertraline 50 mg Tab [CHA] | C1469: 6
A1470: 50331709 | B1470: POUCH 2PC W/INVCLS 1/4" STANDARD | C1470: 6
A1471: 50544594 | B1471: NATURA+ POUCH DRAINABLE TRANSPARANT INVISICLOSE CLOSURE 70MM | C1471: 6
A1472: 50990096 | B1472: GLUC 1.5 CAL 8OZ | C1472: 6
A1473: 49309891 | B1473: MICRO-MIST MED NEB | C1473: 7
A1474: 49312089 | B1474: PENROSE DRAIN, LATEX | C1474: 7
... A7461: 49312600 | B7461: CLIPPER BLADE | C7461: 36
A7462: 49312603 | B7462: 3 | C7462: 36
A7463: 49312643 | B7463: ALLEVYN LIFE FOAM DRESSING 17.2cm x 17.5cm | C7463: 36
A7464: 49312692 | B7464: SURGICAL PATTIES AND STRIPS 1/2" X3" | C7464: 36
A7465: 49365403 | B7465: Culture, Fungus, Blood QST | C7465: 36
A7466: 49555209 | B7466: HEMOCULT TechFee | C7466: 36
A7467: 49582834 | B7467: MAYO CATGUT 1/2 CIRCLE TROCAR POINT | C7467: 36
A7468: 49582836 | B7468: MAYO CAT GUT 1/2 CIRCLE TROCAR | C7468: 36
A7469: 49582863 | B7469: 10 FR ROBINSON CATHETERS | C7469: 36
A7470: 49582973 | B7470: 4-0 VICRYL PC-5 18" | C7470: 36
A7471: 49859323 | B7471: CATHETER,RED RUBBER URETHRAL CATHETERS | C7471: 36
A7472: 49878129 | B7472: CLEAR BODY THREE WAY STOPCOCK LOW PRESSURE | C7472: 36
A7473: 49980752 | B7473: CKMB Profile - CH | C7473: 36
...

Sheet Gross Revenue Percent Change
A1: Gross Revenue - 2023 Prices | B1: 5188679.7
A2: Gross Revenue - 2024 Prices | B2: 5442260.4
A3: Percent Change | B3: =+B2/B1-1 -> 0.048871904
A6: Methodology - see Sheet 3
A8: CDM comparison by two seprate periods

Sheet Sheet3
A1: BillItemId | B1: BillItemLongDesc | C1: 45444 | D1: 45107
A2: 49312618 | B2: ADHESIVE REMOVER WIPES | C2: =VLOOKUP(A2,CDM!$A$2:$C$14090,3,) -> 1 | D2: 1
A3: 49312661 | B3: PADS, TELFA (2"X3") | C3: =VLOOKUP(A3,CDM!$A$2:$C$14090,3,) -> 1 | D3: 1
A4: 49312662 | B4: PADS, TELFA (3"X4") 2132 | C4: =VLOOKUP(A4,CDM!$A$2:$C$14090,3,) -> 1 | D4: 1
A5: 49312668 | B5: 27G X 1-1/4 NEEDLE | C5: =VLOOKUP(A5,CDM!$A$2:$C$14090,3,) -> 1 | D5: 1
A6: 49312672 | B6: ADHESIVE DRESSING 1-1/2"X 3" | C6: =VLOOKUP(A6,CDM!$A$2:$C$14090,3,) -> 1 | D6: 1
A7: 49312699 | B7: PADS, ABDOMINAL 9190 | C7: =VLOOKUP(A7,CDM!$A$2:$C$14090,3,) -> 1 | D7: 1
A8: 49312708 | B8: KLEEN SPEC OTOSCOPE 2.5MM | C8: =VLOOKUP(A8,CDM!$A$2:$C$14090,3,) -> 1 | D8: 1
A9: 49312709 | B9: KLEENSPEC | C9: =VLOOKUP(A9,CDM!$A$2:$C$14090,3,) -> 1 | D9: 1
A10: 49312710 | B10: KLEENSPEC OTOSCOPE ADULT 4.25MM | C10: =VLOOKUP(A10,CDM!$A$2:$C$14090,3,) -> 1 | D10: 1
A11: 49312711 | B11: PILL CHUSHER POUCH | C11: =VLOOKUP(A11,CDM!$A$2:$C$14090,3,) -> 1 | D11: 1
A12: 49312565 | B12: PAD, EYE STERILE 50/BX | C12: =VLOOKUP(A12,CDM!$A$2:$C$14090,3,) -> 1 | D12: 1
A13: 49312706 | B13: DRESSING, TRACHEOTOMY DRAINAGE SPONGES | C13: =VLOOKUP(A13,CDM!$A$2:$C$14090,3,) -> 2 | D13: 2
... A3940: 48174600 | B3940: Cryoablation of Prostate | C3940: =VLOOKUP(A3940,CDM!$A$2:$C$14090,3,) -> 41887 | D3940: 39892
C3941: =SUM(C2:C3940) -> 5442260.4 | D3941: =SUM(D2:D3940) -> 5188679.7
A3944: Methodology - see Sheet 3
A3946: CDM comparison by two seprate periods, Jan 2023-Jun 2023 vs. Jan 2024-Jun 2024
A3947: Based on CDM activties in both periods, and average per charge for each CDM
