Workbook
Name qryECH_OSHPD_Annual_CDM_Prices: #REF!
Name qryECH_OSHPD_Annual_CDM_Prices: 'ECRMC PHARMACY AND IV CDM 2024'!$A$6:$K$6

Sheet Top 50 List
A1: Count | B1: Description | C1: Procedure Type
A2: 210 | B2: X-Ray, Chest, two views | C2: Radiology - X-Ray
A3: 201 | B3: Electrocardiogram | C3: Medicine - Cardiovascular
A4: 167 | B4: Comprehensive Metabolic Panel | C4: Laboratory
A5: 148 | B5: Complete Blood Count, with differential | C5: Laboratory
A6: 142 | B6: Basic Metabolic Panel | C6: Laboratory
A7: 134 | B7: X-Ray, Chest, one view | C7: Radiology - X-Ray
A8: 127 | B8: Prothrombin Time | C8: Laboratory
A9: 127 | B9: Physical Therapy - Therapeutic Exercise | C9: Medicine - Physical Medicine
A10: 121 | B10: Mammography, Screening, Bilateral | C10: Radiology
A11: 119 | B11: Colonoscopy | C11: Surgery
A12: 116 | B12: CT Scan, Head or Brain, without contrast | C12: Radiology - CT Scan
A13: 114 | B13: Urinalysis | C13: Laboratory
... A51: 34 | B51: Culture, Urine | C51: Laboratory

Sheet AB 1045 Form
A1: Hospital Name: El Centro Regional Medical Center
A2: HCAI Facility No: 103130699
A3: Effective Date of Charges: June 1, 2024
A5: In response to requests from hospitals and the public, HCAI has developed this form to assist hospitals in collecting and submitting the average charge for 25 common outpatient procedures performed by hospitals, as required by AB 1045 (Chapter 532, Statutes of 2005). Use of the HCAI form is voluntary, but highly encouraged, as it allows hospitals to report and the public to compare uniform information regarding common outpatient procedures.
A6: Evaluation & Management Services (CPT Codes 99201-99499) | B6: 2024 CPT Code | C6: Average Charge
A7: Emergency Room Visit (low to moderate severity) | B7: 99282 | C7: =+VLOOKUP(B7,CDM_FY24!F:I,4,0) -> 708
A8: Emergency Room Visit (moderate severity) | B8: 99283 | C8: =+VLOOKUP(B8,CDM_FY24!F:I,4,0) -> 1420
A9: Emergency Room Visit (high severity without signigicant threat) | B9: 99284 | C9: =+VLOOKUP(B9,CDM_FY24!F:I,4,0) -> 2250
A10: Emergency Room Visit (high severity with significant threat) | B10: 99285 | C10: =+VLOOKUP(B10,CDM_FY24!F:I,4,0) -> 3425
A11: Outpatient Visit, established patient, 15 minutes | B11: 99213
A12: Laboratory & Pathology Services (CPT Codes 80047-89398) | B12: 2024 CPT Code | C12: Average Charge
A13: Basic Metabolic Panel | B13: 80048 | C13: =+VLOOKUP(B13,CDM_FY24!F:I,4,0) -> 307
A14: Blood Gas Analysis, including 02 saturation | B14: 82805 | C14: =+VLOOKUP(B14,CDM_FY24!F:I,4,0) -> 926
A15: Complete Blood Count, automated | B15: 85027 | C15: =+VLOOKUP(B15,CDM_FY24!F:I,4,0) -> 128
A16: Complete Blood Count, with differential WBC, automated | B16: 85025 | C16: =+VLOOKUP(B16,CDM_FY24!F:I,4,0) -> 150
A17: Comprehensive Metabolic Panel | B17: 80053 | C17: =+VLOOKUP(B17,CDM_FY24!F:I,4,0) -> 370
A18: Creatine Kinase (CK), (CPK), Total | B18: 82550
A19: Lipid Panel | B19: 80061
A20: Partial Thromboplastin Time | B20: 85730
A21: Prothrombin Time | B21: 85610
A22: Thyroid Stimulating Hormone | B22: 84443
A23: Troponin, Quantitative | B23: 84484 | C23: =+VLOOKUP(B23,CDM_FY24!F:I,4,0) -> 295
A24: Urinalysis, without microscopy | B24: 81002 | C24: =+VLOOKUP(B24,CDM_FY24!F:I,4,0) -> 36
A25: Urinalysis, with microscopy | B25: 81000 | C25: =+VLOOKUP(B25,CDM_FY24!F:I,4,0) -> 227
A26: Radiology Services (CPT Codes 70010-79999) | B26: 2024 CPT Code | C26: Average Charge
A27: CT Scan, Abdomen, with contrast | B27: 74160 | C27: =+VLOOKUP(B27,CDM_FY24!F:I,4,0) -> 4091
A28: CT Scan, Head or Brain, without contrast | B28: 70450 | C28: =+VLOOKUP(B28,CDM_FY24!F:I,4,0) -> 3810
A29: CT Scan, Pelvis, with contrast | B29: 72193 | C29: =+VLOOKUP(B29,CDM_FY24!F:I,4,0) -> 3719
A30: Mammography, Screening, Bilateral | B30: 77067 | C30: =+VLOOKUP(B30,CDM_FY24!F:I,4,0) -> 455
A31: MRI, Brain, without contrast, followed by contrast | B31: 70553 | C31: =+VLOOKUP(B31,CDM_FY24!F:I,4,0) -> 6949
A32: Ultrasound, Abdomen, Complete | B32: 76700
A33: Ultrasound, OB, 14 weeks or more, transabdominal | B33: 76805 | C33: =+VLOOKUP(B33,CDM_FY24!F:I,4,0) -> 1127
A34: X-Ray, Lower Back, minimum four views | B34: 72110 | C34: =+VLOOKUP(B34,CDM_FY24!F:I,4,0) -> 1102
A35: X-Ray, Chest, two views | B35: 71046 | C35: =+VLOOKUP(B35,CDM_FY24!F:I,4,0) -> 625
A36: Medicine Services (CPT Codes 90281-99607) | B36: 2024 CPT Code | C36: Average Charge
A37: Cardiac Catheterization, Left Heart, percutaneous | B37: 93452
A38: Echocardiography, Transthoracic, complete, without Doppler | B38: 93307 | C38: =+VLOOKUP(B38,CDM_FY24!F:I,4,0) -> 1898
A39: Electrocardiogram, routine, with interpretation and report | B39: 93000 | C39: =+VLOOKUP(B39,CDM_FY24!F:I,4,0) -> 333.03
A40: Inhalation Treatment, pressurized or nonpressurized | B40: 94640
A41: Physical Therapy, Evaluation | B41: 97161 | C41: =+VLOOKUP(B41,CDM_FY24!F:I,4,0) -> 354
A42: Physical Therapy, Gait Training | B42: 97116 | C42: =+VLOOKUP(B42,CDM_FY24!F:I,4,0) -> 178
A43: Physical Therapy, Therapeutic Exercise | B43: 97110 | C43: =+VLOOKUP(B43,CDM_FY24!F:I,4,0) -> 188
A44: Surgery Services (CPT Codes 10021-69990) | B44: 2024 CPT Code | C44: Average Charge
A45: Arthroscopy, Knee, with meniscectomy (medial or lateral) | B45: 29881
A46: Arthroscopy, Shoulder, with partial acromioplasty | B46: 29826
A47: Carpal Tunnel Surgery | B47: 64721
A48: Cataract Removal with Insertion of Intraocular Lens, 1 Stage | B48: 66984
A49: Colonoscopy, diagnostic | B49: 45378
A50: Colonoscopy, with biopsy | B50: 45380
A51: Colonoscopy, with lesion removal, by snare technique | B51: 45385
A52: Discission, secondary membranous cataract, laser surgery | B52: 66821
A53: Endoscopy, Upper GI, with biopsy | B53: 43239
A54: Endoscopy, Upper GI, diagnostic | B54: 43235
A55: Excision, Breast Lesion, without preoperative radiological marker | B55: 19120
A56: Hernia Repair, Inguinal, 5 years and older | B56: 49505
A57: Injection, Diagnostic or Therapeutic substance, epidural, lumbar | B57: 62322-62323
A58: Injection, Anesthetic or Steroid, transforaminal epidural, lumbar | B58: 64483
A59: Laparoscopic Cholecystectomy | B59: 47562
A60: Tympanostomy (insert ventilating tube, general anesthesia) | B60: 69436
A61: Tonsillectomy with Adenoidectomy, less than 12 years old | B61: 42820
A62: Other Common Outpatient Procedures (list as needed) | B62: 2024 CPT Code | C62: Average Charge
A73: Count of Reported Procedures (minimum 25 required) | C73: =COUNTA(C7:C11,C13:C25,C27:C35,C37:C43,C45:C61,C63:C72) -> 25
A74: Instructions for Completing AB 1045 Common Outpatient Procedure Form
A75: 1. Enter Hospital Name and HCAI Facility Number. Revise Effective Date of Charges, if necessary.
A76: 2. Enter Average Charge for at least 25 commonly performed outpatient procedures. For Evaluation & Management
A77: Services, do not include related ancillary charges. For all other procedures, include related ancillary charges.
A78: NOTE: The CPT codes are included on this form to help identify the listed procedures based on the frequencies
A79: across hospital-based ambulatory surgery data. The average charge for all related services and procedures
A80: (e.g., supplies, drugs, lab, use of operating room, etc.) should be included in the average charge for that procedure.
A81: 3. Do not change procedure descriptions or CPT code references. Use "Other Common Outpatient Procedures"
A82: (rows 62-71) if you are unable to select procedures from list.
A83: 4. Submit completed form as Excel (.xls) file, along with chargemaster and percent change in gross revenue
A84: calculation, by e-mail to chargemaster@hcai.ca.gov or by standard mail on CD.

Sheet ECRMC 2024 CDM
A1: EL CENTRO REGIONAL MEDICAL CENTER
A2: HCAI FACILITY NO. 106130699
A3: CHARGEMASTER LIST EXCLUDING DRUGS SOLD TO PATIENTS AND IV'S SOLD TO PATIENTS- LISTED SEPARATELY
A4: 45444
A7: CDM# | B7: CDM DESC | C7: PRICE
A8: 0000200 | B8: R/B MEDICAL/SURG EAST & WEST | C8: 2357
A9: 0000300 | B9: R/B MED SURG TELEMETRY E/W | C9: 2970
A10: 0000400 | B10: R/B MED SURG TELE & ISOL E/W | C10: 4279
A11: 0000600 | B11: R/B MED SURG ISOLATION E/W | C11: 2970
A12: 0000900 | B12: R/B MEDICAL/SURG NORTH & SOUTH | C12: 2357
A13: 0000900 | B13: R/B MEDICAL/SURG NORTH & SOUTH | C13: 0
A14: 0000901 | B14: R/B MED SURG TELEMETRY N/S | C14: 2970
A15: 0000902 | B15: R/B MED SURG TELE&ISOL N/S | C15: 4279
A16: 0000903 | B16: R/B MED SURG ISOLATION N/S | C16: 2970
A17: 0001000 | B17: R/B ICU | C17: 6031
A18: 0001000 | B18: R/B ICU | C18: 0
A19: 0001100 | B19: R/B ICU ISOLATION | C19: 6393
... A2709: 7392001 | B2709: TELEHEALTH FACILITY FEE CDCR | C2709: 83

Sheet ECRMC PHARMACY AND IV CDM 2024
A1: EL CENTRO REGIONAL MEDICAL CENTER
A2: OSHPD FACILITY NO. 106130699
A3: CHARGEMASTER FOR DRUGS SOLD TO PATIENTS AND INTRAVENOUS SOLUTIONS
A4: 45489
A6: CDM CODE | B6: BRAND_NAME | C6: GENERIC_NAME | D6: AVERAGE WHOLESALE PRICE (AWP) | E6: % MARK-UP | F6: IV_PVAR1_DPU | G6: DISP_DESCR_CDM | H6: DPD_IND | I6: INH_UNIT_COST_DPD | J6: MED_PVAR1_DPD | K6: IV_PVAR1_DPD
A7: 3210301 | B7: NACL 0.45% | C7: NACL 0.45% 1000ML IV BAG | D7: 7.98 | E7: 7.22
A8: 3210303 | B8: NACL 0.9% | C8: NACL 0.9% 250ML IV BAG | D8: 6.44 | E8: 7.22
A9: 3210303 | B9: -NACL 0.9% | C9: NACL 0.9% 250ML IV BAG | D9: 6.44 | E9: 7.22
A10: 3210304 | B10: NACL 0.9% | C10: NACL 0.9% 1000ML IV BAG | D10: 6.97 | E10: 7.22
A11: 3210305 | B11: NACL 3% HYPERTONIC | C11: NACL 3% IV 500ML | D11: 6.91 | E11: 7.22
A12: 3210306 | B12: VITAMIN A&D OINT | C12: VITAMIN A & D OINTMENT | D12: 0.18 | E12: 7.22
A13: 3210315 | B13: ACTIVATED CHARCOAL | C13: ACTIDOSE-AQUA 50 GM LIQUID | D13: 23.65 | E13: 7.22
A14: 3210316 | B14: CHARCOAL/SORBITOL SOLUTION | C14: ACTIDOSE 25 GM LIQUID | D14: 16.70 | E14: 7.22
A15: 3210317 | B15: CHARCOAL/SORBITOL SOLUTION | C15: ACTIDOSE 50 GM LIQUID | D15: 23.65 | E15: 7.22
A16: 3210319 | B16: ALTEPLASE | C16: ACTIVASE 100 MG VIAL | D16: 5218.49 | E16: 4.17
A17: 3210321 | B17: PIOGLITAZONE | C17: ACTOS 15 MG TABLET | D17: 5.78 | E17: 7.22
A18: 3210323 | B18: KETOROLAC TROMETHAMINE 0.5% | C18: ACULAR 0.5% EYE DROPS 5ML | D18: 125.99 | E18: 7.22
... A1818: 3213484 | B1818: TREMELIMUMAB-ACTL | C1818: IMJUDO 300 MG/15 ML VIAL | D1818: 39780.00 | E1818: 3.18

Sheet Gross Revenue Difference
A1: EL CENTRO REGIONAL MEDICAL CENTER
A2: HCAI FACILITY NO. 106130699
A3: Calculation of Percent Change in Gross Revenue
A4: Reporting Period June 1, 2024
B8: Gross Patient Revenue
B9: YTD
A11: 45078 | B11: 6.6182231e+08 | C11: (a)
A13: 45444 | B13: 6.4509606e+08 | C13: (a)
A15: Decrease in Revenue due to changes in utilization, new and/or discontinued services.
B16: =B13-B11 -> -16726256
A18: Increase as % of Gross Patient Revenue | B18: =B16/B11 -> -0.025273032
A22: El Centro Regional Medical Center did not pursue a pricing adjustment as of last year's submission and as such has no substantive variance in gross charges related to price changes.
A25: U:\2024\11 - May\RAT_PROSHEET_0524 - Period 11 FY2024.xlsx | C25: (a)

Sheet CDM_FY24
A2: Dpt# | B2: Dept Name | C2: Pat Type | D2: Charge Cd | E2: Charge Desc | F2: CPT CODE | G2: MTD Usage | H2: MTD Revenue | I2: Avg Price
A3: 3170 | B3: MEDICAL/SURGICAL EAST & WEST | C3: INPATIENT | D3: 0000200 | E3: R/B MEDICAL/SURG EAST & WEST | F3: 0 | G3: 5777 | H3: 13616389 | I3: =IFERROR(H3/G3,0) -> 2357
A4: 3170 | B4: MEDICAL/SURGICAL EAST & WEST | C4: OUTPATIENT | D4: 0000200 | E4: R/B MEDICAL/SURG EAST & WEST | F4: 0 | G4: 1 | H4: 2357 | I4: =IFERROR(H4/G4,0) -> 2357
A5: 3170 | B5: MEDICAL/SURGICAL EAST & WEST | C5: INPATIENT | D5: 0000300 | E5: R/B MED SURG TELEMETRY E/W | F5: 0 | G5: 4630 | H5: 13751100 | I5: =IFERROR(H5/G5,0) -> 2970
A6: 3170 | B6: MEDICAL/SURGICAL EAST & WEST | C6: OUTPATIENT | D6: 0000300 | E6: R/B MED SURG TELEMETRY E/W | F6: 0 | G6: 3 | H6: 8910 | I6: =IFERROR(H6/G6,0) -> 2970
A7: 3170 | B7: MEDICAL/SURGICAL EAST & WEST | C7: INPATIENT | D7: 0000400 | E7: R/B MED SURG TELE & ISOL E/W | F7: 0 | G7: 848 | H7: 3628592 | I7: =IFERROR(H7/G7,0) -> 4279
A8: 3170 | B8: MEDICAL/SURGICAL EAST & WEST | C8: INPATIENT | D8: 0000600 | E8: R/B MED SURG ISOLATION E/W | F8: 0 | G8: 1208 | H8: 3587760 | I8: =IFERROR(H8/G8,0) -> 2970
A9: 3170 | B9: MEDICAL/SURGICAL EAST & WEST | C9: INPATIENT | D9: 0000900 | E9: R/B MEDICAL/SURG NORTH & SOUTH | F9: 0 | G9: 1501 | H9: 3537857 | I9: =IFERROR(H9/G9,0) -> 2357
A10: 3170 | B10: MEDICAL/SURGICAL EAST & WEST | C10: OUTPATIENT | D10: 0000900 | E10: R/B MEDICAL/SURG NORTH & SOUTH | F10: 0 | G10: 0 | H10: 0 | I10: =IFERROR(H10/G10,0) -> 0
A11: 3170 | B11: MEDICAL/SURGICAL EAST & WEST | C11: INPATIENT | D11: 0000901 | E11: R/B MED SURG TELEMETRY N/S | F11: 0 | G11: 566 | H11: 1681020 | I11: =IFERROR(H11/G11,0) -> 2970
A12: 3170 | B12: MEDICAL/SURGICAL EAST & WEST | C12: INPATIENT | D12: 0000902 | E12: R/B MED SURG TELE&ISOL N/S | F12: 0 | G12: 65 | H12: 278135 | I12: =IFERROR(H12/G12,0) -> 4279
A13: 3170 | B13: MEDICAL/SURGICAL EAST & WEST | C13: INPATIENT | D13: 0000903 | E13: R/B MED SURG ISOLATION N/S | F13: 0 | G13: 145 | H13: 430650 | I13: =IFERROR(H13/G13,0) -> 2970
A14: 3010 | B14: ICU | C14: INPATIENT | D14: 0001000 | E14: R/B ICU | F14: 0 | G14: 1009 | H14: 6085279 | I14: =IFERROR(H14/G14,0) -> 6031
... A21: 3290 | B21: PEDIATRICS | C21: INPATIENT | D21: 0004200 | E21: R/B PEDIATRICS | F21: 0 | G21: 0 | H21: 0 | I21: =IFERROR(H21/G21,0) -> 0
A22: 8721 | B22: POPULATION HEALTH | C22: OUTPATIENT | D22: 110100 | E22: ECM IN-PERSON: PROVIDED BY CLINICAL STAFF | F22: G9008 | G22: 23 | H22: 9200 | I22: =IFERROR(H22/G22,0) -> 400
A23: 8721 | B23: POPULATION HEALTH | C23: OUTPATIENT | D23: 110101 | E23: ECM PHONE/TELEHEALTH:PROVIDED BY CLINICAL STAFF | F23: G9008 | G23: 336 | H23: 134400 | I23: =IFERROR(H23/G23,0) -> 400
A24: 8721 | B24: POPULATION HEALTH | C24: OUTPATIENT | D24: 110102 | E24: ECM IN-PERSON: PROVIDED BY NON-CLINICAL STAFF | F24: G9012 | G24: 19 | H24: 7600 | I24: =IFERROR(H24/G24,0) -> 400
A25: 8721 | B25: POPULATION HEALTH | C25: OUTPATIENT | D25: 110103 | E25: ECM PHONE/TELEHEALTH:PROVIDED NON-CLINICAL STAFF | F25: G9012 | G25: 471 | H25: 188400 | I25: =IFERROR(H25/G25,0) -> 400
A26: 8721 | B26: POPULATION HEALTH | C26: OUTPATIENT | D26: 110104 | E26: ECM OUTREACH | F26: G9012 | G26: 1847 | H26: 738800 | I26: =IFERROR(H26/G26,0) -> 400
A27: 8721 | B27: POPULATION HEALTH | C27: OUTPATIENT | D27: 110105 | E27: SUD SELF-MANAGEMENT EDUCATION 30 MIN FACE-FACE | F27: 98960 | G27: 178 | H27: 11863.7 | I27: =IFERROR(H27/G27,0) -> 66.65
A28: 4010 | B28: EMERGENCY ROOM | C28: INPATIENT | D28: 1000000 | E28: CLASS 5 EMERGENCY ROOM VISIT | F28: 99285 | G28: 2847 | H28: 9750975 | I28: =IFERROR(H28/G28,0) -> 3425
A29: 4010 | B29: EMERGENCY ROOM | C29: OUTPATIENT | D29: 1000000 | E29: CLASS 5 EMERGENCY ROOM VISIT | F29: 99285 | G29: 2954 | H29: 10117450 | I29: =IFERROR(H29/G29,0) -> 3425
A30: 4010 | B30: EMERGENCY ROOM | C30: INPATIENT | D30: 1000100 | E30: CLASS 4 EMERGENCY ROOM VISIT | F30: 99284 | G30: 9 | H30: 20250 | I30: =IFERROR(H30/G30,0) -> 2250
A31: 4010 | B31: EMERGENCY ROOM | C31: OUTPATIENT | D31: 1000100 | E31: CLASS 4 EMERGENCY ROOM VISIT | F31: 99284 | G31: 11555 | H31: 25998750 | I31: =IFERROR(H31/G31,0) -> 2250
A32: 4010 | B32: EMERGENCY ROOM | C32: INPATIENT | D32: 1000200 | E32: CLASS 3 EMERGENCY ROOM VISIT | F32: 99283 | G32: 3 | H32: 4260 | I32: =IFERROR(H32/G32,0) -> 1420
A33: 4010 | B33: EMERGENCY ROOM | C33: OUTPATIENT | D33: 1000200 | E33: CLASS 3 EMERGENCY ROOM VISIT | F33: 99283 | G33: 13427 | H33: 19066340 | I33: =IFERROR(H33/G33,0) -> 1420
A34: 4010 | B34: EMERGENCY ROOM | C34: INPATIENT | D34: 1000300 | E34: CLASS 2 EMERGENCY ROOM VISIT | F34: 99282 | G34: 1 | H34: 708 | I34: =IFERROR(H34/G34,0) -> 708
A35: 4010 | B35: EMERGENCY ROOM | C35: OUTPATIENT | D35: 1000300 | E35: CLASS 2 EMERGENCY ROOM VISIT | F35: 99282 | G35: 1887 | H35: 1335996 | I35: =IFERROR(H35/G35,0) -> 708
A36: 4010 | B36: EMERGENCY ROOM | C36: OUTPATIENT | D36: 1000400 | E36: CLASS 1 EMERGENCY ROOM VISIT | F36: 99281 | G36: 1044 | H36: 316332 | I36: =IFERROR(H36/G36,0) -> 303
A37: 4010 | B37: EMERGENCY ROOM | C37: OUTPATIENT | D37: 1000402 | E37: MEDHOST E&M 1 99281 STATISTIC | F37: 0 | G37: 1539 | H37: 0 | I37: =IFERROR(H37/G37,0) -> 0
A38: 4010 | B38: EMERGENCY ROOM | C38: INPATIENT | D38: 1000403 | E38: MEDHOST E&M 2 99282 STATISTIC | F38: 0 | G38: 1 | H38: 0 | I38: =IFERROR(H38/G38,0) -> 0
... A55: 4010 | B55: EMERGENCY ROOM | C55: OUTPATIENT | D55: 1001001 | E55: CRITICAL CARE EACH ADD 30 MIN | F55: 99292 | G55: 60 | H55: 138360 | I55: =IFERROR(H55/G55,0) -> 2306
A56: 4010 | B56: EMERGENCY ROOM | C56: INPATIENT | D56: 1001002 | E56: TRAUMA CODE ACTIVATION | F56: G0390 | G56: 2 | H56: 12520 | I56: =IFERROR(H56/G56,0) -> 6260
A57: 4010 | B57: EMERGENCY ROOM | C57: OUTPATIENT | D57: 1001002 | E57: TRAUMA CODE ACTIVATION | F57: G0390 | G57: 27 | H57: 169020 | I57: =IFERROR(H57/G57,0) -> 6260
A58: 4470 | B58: MEDICAL SUPPLIES SOLD TO PATIENTS | C58: INPATIENT | D58: 1001300 | E58: OXYGEN | F58: 0 | G58: 154 | H58: 8932 | I58: =IFERROR(H58/G58,0) -> 58
A59: 4470 | B59: MEDICAL SUPPLIES SOLD TO PATIENTS | C59: OUTPATIENT | D59: 1001300 | E59: OXYGEN | F59: 0 | G59: 212 | H59: 12296 | I59: =IFERROR(H59/G59,0) -> 58
A60: 4010 | B60: EMERGENCY ROOM | C60: INPATIENT | D60: 1001901 | E60: ER NON CHARGEABLE SUPPLIES,NCH | F60: 0 | G60: 164 | H60: 0 | I60: =IFERROR(H60/G60,0) -> 0
A61: 4010 | B61: EMERGENCY ROOM | C61: OUTPATIENT | D61: 1001901 | E61: ER NON CHARGEABLE SUPPLIES,NCH | F61: 0 | G61: 322 | H61: 0 | I61: =IFERROR(H61/G61,0) -> 0
A62: 4010 | B62: EMERGENCY ROOM | C62: INPATIENT | D62: 1001902 | E62: ER NO CHG. LAB CHG. | F62: 0 | G62: 435 | H62: 0 | I62: =IFERROR(H62/G62,0) -> 0
A63: 4010 | B63: EMERGENCY ROOM | C63: OUTPATIENT | D63: 1001902 | E63: ER NO CHG. LAB CHG. | F63: 0 | G63: 1487 | H63: 0 | I63: =IFERROR(H63/G63,0) -> 0
A64: 4010 | B64: EMERGENCY ROOM | C64: INPATIENT | D64: 1001903 | E64: ER NO CHG. IV INSERTION | F64: 36000 | G64: 1215 | H64: 0 | I64: =IFERROR(H64/G64,0) -> 0
A65: 4010 | B65: EMERGENCY ROOM | C65: OUTPATIENT | D65: 1001903 | E65: ER NO CHG. IV INSERTION | F65: 36000 | G65: 6889 | H65: 0 | I65: =IFERROR(H65/G65,0) -> 0
A66: 4010 | B66: EMERGENCY ROOM | C66: INPATIENT | D66: 1001905 | E66: ER NO CHG. RT CHG CPR | F66: 0 | G66: 18 | H66: 0 | I66: =IFERROR(H66/G66,0) -> 0
A67: 4010 | B67: EMERGENCY ROOM | C67: OUTPATIENT | D67: 1001905 | E67: ER NO CHG. RT CHG CPR | F67: 0 | G67: 49 | H67: 0 | I67: =IFERROR(H67/G67,0) -> 0
A68: 4010 | B68: EMERGENCY ROOM | C68: INPATIENT | D68: 1001906 | E68: ER NO CHG. PROCEDURE EKG CHG | F68: 0 | G68: 1873 | H68: 0 | I68: =IFERROR(H68/G68,0) -> 0
A69: 4010 | B69: EMERGENCY ROOM | C69: OUTPATIENT | D69: 1001906 | E69: ER NO CHG. PROCEDURE EKG CHG | F69: 0 | G69: 5939 | H69: 0 | I69: =IFERROR(H69/G69,0) -> 0
... A95: 4010 | B95: EMERGENCY ROOM | C95: OUTPATIENT | D95: 1003006 | E95: IV INF CONCURRENT THER/PROF/DI | F95: 96368 | G95: 57 | H95: 15903 | I95: =IFERROR(H95/G95,0) -> 279
A96: 4010 | B96: EMERGENCY ROOM | C96: OUTPATIENT | D96: 1003009 | E96: INTRAVENOUS INFUSION, BAMLANIVIMAB AND ETESEVIMAB | F96: M0245 | G96: 0 | H96: 0 | I96: =IFERROR(H96/G96,0) -> 0
A97: 4010 | B97: EMERGENCY ROOM | C97: OUTPATIENT | D97: 1003010 | E97: ADMIN SOTROVIMAB INFUSION | F97: M0247 | G97: 0 | H97: 0 | I97: =IFERROR(H97/G97,0) -> 0
A98: 4010 | B98: EMERGENCY ROOM | C98: OUTPATIENT | D98: 1003011 | E98: BEBTELOVIMAB ADMINISTRATION | F98: M0222 | G98: 0 | H98: 0 | I98: =IFERROR(H98/G98,0) -> 0
A99: 4010 | B99: EMERGENCY ROOM | C99: INPATIENT | D99: 1003100 | E99: MODERATE SED 1ST 30 MIN | F99: 0 | G99: 5 | H99: 3195 | I99: =IFERROR(H99/G99,0) -> 639
A100: 4010 | B100: EMERGENCY ROOM | C100: OUTPATIENT | D100: 1003100 | E100: MODERATE SED 1ST 30 MIN | F100: 0 | G100: 68 | H100: 43452 | I100: =IFERROR(H100/G100,0) -> 639
A101: 4010 | B101: EMERGENCY ROOM | C101: OUTPATIENT | D101: 1003101 | E101: MODERATE SEDATION ADD 15 MIN | F101: 0 | G101: 4 | H101: 1240 | I101: =IFERROR(H101/G101,0) -> 310
A102: 4010 | B102: EMERGENCY ROOM | C102: INPATIENT | D102: 1003500 | E102: ER PROCEDURE 15 MIN | F102: 0 | G102: 1 | H102: 492 | I102: =IFERROR(H102/G102,0) -> 492
A103: 4010 | B103: EMERGENCY ROOM | C103: OUTPATIENT | D103: 1003500 | E103: ER PROCEDURE 15 MIN | F103: 0 | G103: 4 | H103: 1968 | I103: =IFERROR(H103/G103,0) -> 492
A104: 4010 | B104: EMERGENCY ROOM | C104: OUTPATIENT | D104: 1003800 | E104: ADMIN INFLUENZA VACCINE | F104: G0008 | G104: 0 | H104: 0 | I104: =IFERROR(H104/G104,0) -> 0
A105: 4010 | B105: EMERGENCY ROOM | C105: OUTPATIENT | D105: 1003901 | E105: ADMIN HEPATITIS B VACCINE | F105: G0010 | G105: 0 | H105: 0 | I105: =IFERROR(H105/G105,0) -> 0
A106: 4010 | B106: EMERGENCY ROOM | C106: INPATIENT | D106: 1004000 | E106: URINE MULTI-STICK EACH | F106: 81003 | G106: 0 | H106: 0 | I106: =IFERROR(H106/G106,0) -> 0
A107: 4010 | B107: EMERGENCY ROOM | C107: OUTPATIENT | D107: 1004000 | E107: URINE MULTI-STICK EACH | F107: 81003 | G107: 0 | H107: 0 | I107: =IFERROR(H107/G107,0) -> 0
A108: 4010 | B108: EMERGENCY ROOM | C108: INPATIENT | D108: 1004100 | E108: IV PUSH SEQUENTIAL DIFF DRUG | F108: 96375 | G108: 2243 | H108: 610096 | I108: =IFERROR(H108/G108,0) -> 272
A109: 4010 | B109: EMERGENCY ROOM | C109: OUTPATIENT | D109: 1004100 | E109: IV PUSH SEQUENTIAL DIFF DRUG | F109: 96375 | G109: 6787 | H109: 1846064 | I109: =IFERROR(H109/G109,0) -> 272
A110: 4010 | B110: EMERGENCY ROOM | C110: INPATIENT | D110: 1004101 | E110: IV PUSH SEQ SAME DRUG AFTR 30M | F110: 96376 | G110: 466 | H110: 130014 | I110: =IFERROR(H110/G110,0) -> 279
A111: 4010 | B111: EMERGENCY ROOM | C111: OUTPATIENT | D111: 1004101 | E111: IV PUSH SEQ SAME DRUG AFTR 30M | F111: 96376 | G111: 1533 | H111: 427707 | I111: =IFERROR(H111/G111,0) -> 279
A112: 4010 | B112: EMERGENCY ROOM | C112: INPATIENT | D112: 1004700 | E112: INJ S/C OR IM SEP PROCEDURE | F112: 96372 | G112: 25 | H112: 5725 | I112: =IFERROR(H112/G112,0) -> 229
A113: 4010 | B113: EMERGENCY ROOM | C113: OUTPATIENT | D113: 1004700 | E113: INJ S/C OR IM SEP PROCEDURE | F113: 96372 | G113: 160 | H113: 36640 | I113: =IFERROR(H113/G113,0) -> 229
A114: 4010 | B114: EMERGENCY ROOM | C114: INPATIENT | D114: 1004800 | E114: ULTRASOUND,BLADDER CAPACITY | F114: 51798 | G114: 78 | H114: 15054 | I114: =IFERROR(H114/G114,0) -> 193
A115: 4010 | B115: EMERGENCY ROOM | C115: OUTPATIENT | D115: 1004800 | E115: ULTRASOUND,BLADDER CAPACITY | F115: 51798 | G115: 290 | H115: 55970 | I115: =IFERROR(H115/G115,0) -> 193
A116: 4010 | B116: EMERGENCY ROOM | C116: INPATIENT | D116: 1004811 | E116: ER PROCEDURE I | F116: 0 | G116: 45 | H116: 9945 | I116: =IFERROR(H116/G116,0) -> 221
A117: 4010 | B117: EMERGENCY ROOM | C117: OUTPATIENT | D117: 1004811 | E117: ER PROCEDURE I | F117: 0 | G117: 133 | H117: 29393 | I117: =IFERROR(H117/G117,0) -> 221
... A165: 4072 | B165: DIABETES CLINIC | C165: OUTPATIENT | D165: 1100302 | E165: DIAB SELFMGMT GRP TRN30 5-8PTS | F165: 98962 | G165: 224 | H165: 10080 | I165: =IFERROR(H165/G165,0) -> 45
A166: 4072 | B166: DIABETES CLINIC | C166: OUTPATIENT | D166: 1100800 | E166: 1ST MDPP CORE SESSIONS | F166: G9873 | G166: 0 | H166: 0 | I166: =IFERROR(H166/G166,0) -> 0
A167: 8881 | B167: DIABETES PREVENTION PROGRAM | C167: OUTPATIENT | D167: 1100800 | E167: 1ST MDPP CORE SESSIONS | F167: G9873 | G167: 1 | H167: 91 | I167: =IFERROR(H167/G167,0) -> 91
A168: 4072 | B168: DIABETES CLINIC | C168: OUTPATIENT | D168: 1100801 | E168: FOUR MDPP CORE SESSIONS | F168: G9874 | G168: 0 | H168: 0 | I168: =IFERROR(H168/G168,0) -> 0
A169: 8881 | B169: DIABETES PREVENTION PROGRAM | C169: OUTPATIENT | D169: 1100801 | E169: FOUR MDPP CORE SESSIONS | F169: G9874 | G169: 1 | H169: 182 | I169: =IFERROR(H169/G169,0) -> 182
A170: 8881 | B170: DIABETES PREVENTION PROGRAM | C170: OUTPATIENT | D170: 1100802 | E170: NINE TOTAL MDPP CORE SESSIONS | F170: G9875 | G170: 0 | H170: 0 | I170: =IFERROR(H170/G170,0) -> 0
A171: 8881 | B171: DIABETES PREVENTION PROGRAM | C171: OUTPATIENT | D171: 1100811 | E171: EM 5 PERCENT WL | F171: G9880 | G171: 1 | H171: 168 | I171: =IFERROR(H171/G171,0) -> 168
A172: 8881 | B172: DIABETES PREVENTION PROGRAM | C172: OUTPATIENT | D172: 1100815 | E172: 2ND MDPP CORE SESSION | F172: G9891 | G172: 1 | H172: 1 | I172: =IFERROR(H172/G172,0) -> 1
A173: 8881 | B173: DIABETES PREVENTION PROGRAM | C173: OUTPATIENT | D173: 1100816 | E173: 3RD MDPP CORE SESSION | F173: G9891 | G173: 1 | H173: 1 | I173: =IFERROR(H173/G173,0) -> 1
A174: 8881 | B174: DIABETES PREVENTION PROGRAM | C174: OUTPATIENT | D174: 1100817 | E174: 5TH MDPP CORE SESSION | F174: G9891 | G174: 1 | H174: 1 | I174: =IFERROR(H174/G174,0) -> 1
A175: 8881 | B175: DIABETES PREVENTION PROGRAM | C175: OUTPATIENT | D175: 1100818 | E175: 6TH MDPP CORE SESSION | F175: G9891 | G175: 1 | H175: 1 | I175: =IFERROR(H175/G175,0) -> 1
A176: 8881 | B176: DIABETES PREVENTION PROGRAM | C176: OUTPATIENT | D176: 1100819 | E176: 7TH MDPP CORE SESSION | F176: G9891 | G176: 0 | H176: 0 | I176: =IFERROR(H176/G176,0) -> 0
A177: 8881 | B177: DIABETES PREVENTION PROGRAM | C177: OUTPATIENT | D177: 1100820 | E177: 8TH MDPP CORE SESSION | F177: G9891 | G177: 1 | H177: 1 | I177: =IFERROR(H177/G177,0) -> 1
A178: 8794 | B178: EMPLOYEE HEALTH | C178: OUTPATIENT | D178: 1101003 | E178: QUANTITATIVE FIT TESTING | F178: 0 | G178: 138 | H178: 8970 | I178: =IFERROR(H178/G178,0) -> 65
A179: 4390 | B179: O/P ANTENATAL | C179: OUTPATIENT | D179: 1200101 | E179: IV INF INIT HR THER/PROF/DIAG | F179: 96365 | G179: 0 | H179: 0 | I179: =IFERROR(H179/G179,0) -> 0
A180: 4390 | B180: O/P ANTENATAL | C180: OUTPATIENT | D180: 1200200 | E180: INJ SUBCUTANEOUS/INTRAMUSCULAR | F180: 96372 | G180: 0 | H180: 0 | I180: =IFERROR(H180/G180,0) -> 0
A181: 4400 | B181: LABOR & DELIVERY | C181: INPATIENT | D181: 1420100 | E181: HOURLY OBSERVATION - OB | F181: 0 | G181: 0 | H181: 0 | I181: =IFERROR(H181/G181,0) -> 0
A182: 4400 | B182: LABOR & DELIVERY | C182: OUTPATIENT | D182: 1420100 | E182: HOURLY OBSERVATION - OB | F182: 0 | G182: 1 | H182: 191 | I182: =IFERROR(H182/G182,0) -> 191
A183: 4400 | B183: LABOR & DELIVERY | C183: INPATIENT | D183: 1420101 | E183: DIRECT ADMIT TO OBSERVATION-OB | F183: G0379 | G183: 0 | H183: 0 | I183: =IFERROR(H183/G183,0) -> 0
A184: 4400 | B184: LABOR & DELIVERY | C184: OUTPATIENT | D184: 1420101 | E184: DIRECT ADMIT TO OBSERVATION-OB | F184: G0379 | G184: 0 | H184: 0 | I184: =IFERROR(H184/G184,0) -> 0
A185: 3170 | B185: MEDICAL/SURGICAL EAST & WEST | C185: INPATIENT | D185: 1420200 | E185: HOURLY OBSERVATN-MED SURG E/W | F185: 0 | G185: 790 | H185: 1210909 | I185: =IFERROR(H185/G185,0) -> 1532.7962
A186: 3170 | B186: MEDICAL/SURGICAL EAST & WEST | C186: OUTPATIENT | D186: 1420200 | E186: HOURLY OBSERVATN-MED SURG E/W | F186: 0 | G186: 2876 | H186: 5078593.4 | I186: =IFERROR(H186/G186,0) -> 1765.8531
A187: 3170 | B187: MEDICAL/SURGICAL EAST & WEST | C187: INPATIENT | D187: 1420250 | E187: HOURLY OBSERVATN-MED SURG N/S | F187: 0 | G187: 107 | H187: 168521.6 | I187: =IFERROR(H187/G187,0) -> 1574.9682
A188: 3170 | B188: MEDICAL/SURGICAL EAST & WEST | C188: OUTPATIENT | D188: 1420250 | E188: HOURLY OBSERVATN-MED SURG N/S | F188: 0 | G188: 702 | H188: 1330075.4 | I188: =IFERROR(H188/G188,0) -> 1894.6943
A189: 3010 | B189: ICU | C189: INPATIENT | D189: 1420300 | E189: HOURLY OBSERVATION - ICU | F189: 0 | G189: 17 | H189: 72904.4 | I189: =IFERROR(H189/G189,0) -> 4288.4941
A190: 3010 | B190: ICU | C190: OUTPATIENT | D190: 1420300 | E190: HOURLY OBSERVATION - ICU | F190: 0 | G190: 3 | H190: 11696.6 | I190: =IFERROR(H190/G190,0) -> 3898.8667
A191: 3290 | B191: PEDIATRICS | C191: OUTPATIENT | D191: 1420400 | E191: HOURLY OBSERVATION - PED | F191: 0 | G191: 0 | H191: 0 | I191: =IFERROR(H191/G191,0) -> 0
A192: 4470 | B192: MEDICAL SUPPLIES SOLD TO PATIENTS | C192: INPATIENT | D192: 1510300 | E192: SUTURE MONOCRYL 3-0 Y936H | F192: 0 | G192: 3 | H192: 120 | I192: =IFERROR(H192/G192,0) -> 40
A193: 4470 | B193: MEDICAL SUPPLIES SOLD TO PATIENTS | C193: OUTPATIENT | D193: 1510300 | E193: SUTURE MONOCRYL 3-0 Y936H | F193: 0 | G193: 6 | H193: 240 | I193: =IFERROR(H193/G193,0) -> 40
A194: 4470 | B194: MEDICAL SUPPLIES SOLD TO PATIENTS | C194: INPATIENT | D194: 1510500 | E194: SUTURE MONOCRYL 2-0 Y351H | F194: 0 | G194: 0 | H194: 0 | I194: =IFERROR(H194/G194,0) -> 0
A195: 4470 | B195: MEDICAL SUPPLIES SOLD TO PATIENTS | C195: OUTPATIENT | D195: 1510500 | E195: SUTURE MONOCRYL 2-0 Y351H | F195: 0 | G195: 3 | H195: 60 | I195: =IFERROR(H195/G195,0) -> 20
...

Sheet Sheet1
A2: DEPT# | B2: DEPT NAME | C2: CDM# | D2: CDM DESC | E2: CDM BILLING DESC | F2: TOTAL COST | G2: PRICE | H2: EFF DT | I2: DEFAULT CPT | J2: DEFAULT CPT MOD | K2: MCARE OVR CPT | L2: MCARE OVR MOD | M2: MCAL OVR CPT | N2: MCAL OVR MOD | O2: DEFAULT REV CD | P2: MCARE OVR REV CD | Q2: MCAL OVR REV CD | R2: Y ECRMC - CHARGE CODE LIST (FILE)
A3: 3170 | B3: MEDICAL/SURGICAL EAST & WEST | C3: 0000200 | D3: R/B MEDICAL/SURG EAST & WEST | E3: R/B - MED SURG SEMI-PRIVATE EAST & WEST | F3: **N/A** | G3: 2357 | H3: 41091 | O3: 120 | Q3: 121
A4: 3170 | B4: MEDICAL/SURGICAL EAST & WEST | C4: 0000300 | D4: R/B MED SURG TELEMETRY E/W | E4: R/B - MED SURG TELEMETRY EAST & WEST | F4: **N/A** | G4: 2970 | H4: 41091 | O4: 120 | Q4: 121
A5: 3170 | B5: MEDICAL/SURGICAL EAST & WEST | C5: 0000400 | D5: R/B MED SURG TELE & ISOL E/W | E5: R/B - MED SURG TELEMETRY & ISOLATION EAST & WEST | F5: **N/A** | G5: 4279 | H5: 41091 | O5: 164 | Q5: 111
A6: 3170 | B6: MEDICAL/SURGICAL EAST & WEST | C6: 0000600 | D6: R/B MED SURG ISOLATION E/W | E6: R/B MED SURG ISOLATION EAST & WEST | F6: **N/A** | G6: 2970 | H6: 41091 | O6: 164 | Q6: 111
A7: 3170 | B7: MEDICAL/SURGICAL EAST & WEST | C7: 0000900 | D7: R/B MEDICAL/SURG NORTH & SOUTH | E7: R/B MEDICAL/SURGICAL SEMI-PRIVATE NORTH & SOUTH | F7: **N/A** | G7: 2357 | H7: 41456 | O7: 120 | Q7: 121
A8: 3170 | B8: MEDICAL/SURGICAL EAST & WEST | C8: 0000901 | D8: R/B MED SURG TELEMETRY N/S | E8: R/B MED SURG TELEMETRY NORTH & SOUTH | F8: **N/A** | G8: 2970 | H8: 41456 | O8: 120 | Q8: 121
A9: 3170 | B9: MEDICAL/SURGICAL EAST & WEST | C9: 0000902 | D9: R/B MED SURG TELE&ISOL N/S | E9: R/B MED SURG TELEMETRY & ISOLATION NORTH & SOUTH | F9: **N/A** | G9: 4279 | H9: 41456 | O9: 164 | Q9: 111
A10: 3170 | B10: MEDICAL/SURGICAL EAST & WEST | C10: 0000903 | D10: R/B MED SURG ISOLATION N/S | E10: R/B MED SURG ISOLATION NORTH & SOUTH | F10: **N/A** | G10: 2970 | H10: 41456 | O10: 164 | Q10: 111
A11: 3010 | B11: ICU | C11: 0001000 | D11: R/B ICU | E11: R/B ICU | F11: **N/A** | G11: 6031 | H11: 41091 | O11: 200
A12: 3010 | B12: ICU | C12: 0001100 | D12: R/B ICU ISOLATION | E12: R/B ICU ISOLATION | F12: **N/A** | G12: 6393 | H12: 41091 | O12: 200
A13: 3150 | B13: DEFINITIVE OBSERVATION UNIT | C13: 0001200 | D13: R/B DOU ISOLATION | E13: R/B DOU ISOLATION | F13: **N/A** | G13: 4478 | H13: 41149 | O13: 110 | Q13: 206
A14: 3150 | B14: DEFINITIVE OBSERVATION UNIT | C14: 0001300 | D14: R/B DOU | E14: R/B DOU | F14: **N/A** | G14: 3999 | H14: 41149 | O14: 110 | Q14: 206
A15: 3380 | B15: OBSTETRICS | C15: 0002200 | D15: R/B OB | E15: R/B OB | F15: **N/A** | G15: 2631 | H15: 41149 | O15: 122
A16: 3380 | B16: OBSTETRICS | C16: 0002600 | D16: R/B OB ISOLATION | E16: R/B OB ISOLATION | F16: **N/A** | G16: 3622 | H16: 41149 | O16: 164 | Q16: 112
A17: 3530 | B17: NURSERY | C17: 0003000 | D17: R/B NEWBORN I NORMAL NEWBORN | E17: R/B NEWBORN I NORMAL NEWBORN | F17: **N/A** | G17: 1653 | H17: 41091 | O17: 171
A18: 3530 | B18: NURSERY | C18: 0003100 | D18: R/B NEWBORN II CONTINUING CARE | E18: R/B NEWBORN II CONTINUING CARE | F18: **N/A** | G18: 2269 | H18: 42186 | O18: 172
A19: 3530 | B19: NURSERY | C19: 0003300 | D19: R/B NEWBORN III INTERMEDIATE | E19: R/B NEWBORN III INTERMEDIATE CARE | F19: **N/A** | G19: 3693 | H19: 41149 | O19: 173
A20: 3290 | B20: PEDIATRICS | C20: 0004200 | D20: R/B PEDIATRICS | E20: R/B PEDS SEMI-PRIVATE | F20: **N/A** | G20: 2378 | H20: 41091 | O20: 123
A21: 3290 | B21: PEDIATRICS | C21: 0004600 | D21: R/B PEDS ISOLATION | E21: R/B PEDS ISOLATION | F21: **N/A** | G21: 2970 | H21: 41091 | O21: 164 | Q21: 113
A22: 4010 | B22: EMERGENCY ROOM | C22: 1000000 | D22: CLASS 5 EMERGENCY ROOM VISIT | E22: CLASS 5 EMERGENCY ROOM VISIT | F22: **N/A** | G22: 3425 | H22: 44197 | I22: 99285 | J22: 25 | M22: Z7502 | O22: 450
A23: 4010 | B23: EMERGENCY ROOM | C23: 1000100 | D23: CLASS 4 EMERGENCY ROOM VISIT | E23: CLASS IV EXTENSIVE | F23: **N/A** | G23: 2250 | H23: 44197 | I23: 99284 | J23: 25 | M23: Z7502 | O23: 450
A24: 4010 | B24: EMERGENCY ROOM | C24: 1000200 | D24: CLASS 3 EMERGENCY ROOM VISIT | E24: CLASS III MODERATE | F24: **N/A** | G24: 1420 | H24: 44197 | I24: 99283 | J24: 25 | M24: Z7502 | O24: 450
A25: 4010 | B25: EMERGENCY ROOM | C25: 1000300 | D25: CLASS 2 EMERGENCY ROOM VISIT | E25: CLASS II ROUTINE | F25: **N/A** | G25: 708 | H25: 44197 | I25: 99282 | J25: 25 | M25: Z7502 | O25: 450
A26: 4010 | B26: EMERGENCY ROOM | C26: 1000400 | D26: CLASS 1 EMERGENCY ROOM VISIT | E26: CLASS 1 EMERGENCY ROOM VISIT | F26: **N/A** | G26: 303 | H26: 44197 | I26: 99281 | J26: 25 | M26: Z7502 | O26: 450
A27: 4010 | B27: EMERGENCY ROOM | C27: 1000401 | D27: MEDHOST E&M LEVEL STATISTIC | E27: MEDHOST E&M LEVEL STATISTIC | F27: **N/A** | G27: 0 | H27: 42552 | O27: 450
A28: 4010 | B28: EMERGENCY ROOM | C28: 1000402 | D28: MEDHOST E&M 1 99281 STATISTIC | E28: MEDHOST E&M 1 99281 STATISTIC | F28: **N/A** | G28: 0 | H28: 42552 | O28: 450
A29: 4010 | B29: EMERGENCY ROOM | C29: 1000403 | D29: MEDHOST E&M 2 99282 STATISTIC | E29: MEDHOST E&M 2 99282 STATISTIC | F29: **N/A** | G29: 0 | H29: 42552 | O29: 450
A30: 4010 | B30: EMERGENCY ROOM | C30: 1000404 | D30: MEDHOST E&M 3 99283 STATISTIC | E30: MEDHOST E&M 3 99283 STATISTIC | F30: **N/A** | G30: 0 | H30: 42552 | O30: 450
A31: 4010 | B31: EMERGENCY ROOM | C31: 1000405 | D31: MEDHOST E&M 4 99284 STATISTIC | E31: MEDHOST E&M 4 99284 STATISTIC | F31: **N/A** | G31: 0 | H31: 42552 | O31: 450
A32: 4010 | B32: EMERGENCY ROOM | C32: 1000406 | D32: MEDHOST E&M 5 99285 STATISTIC | E32: MEDHOST E&M 5 99285 STATISTIC | F32: **N/A** | G32: 0 | H32: 42552 | O32: 450
A33: 4010 | B33: EMERGENCY ROOM | C33: 1000407 | D33: MEDHOST E&M 6 99291 STATISTIC | E33: MEDHOST E&M 6 99291 STATISTIC | F33: **N/A** | G33: 0 | H33: 42552 | O33: 450
A34: 4010 | B34: EMERGENCY ROOM | C34: 1000408 | D34: MEDHOST E&M 7 99292 STATISTIC | E34: MEDHOST E&M 7 99292 STATISTIC | F34: **N/A** | G34: 0 | H34: 42552 | O34: 450
A35: 4010 | B35: EMERGENCY ROOM | C35: 1000800 | D35: EMPLOYEE HEALTH | E35: EMPLOYEE HEALTH | F35: **N/A** | G35: 61 | H35: 42917 | O35: 450
A36: 4010 | B36: EMERGENCY ROOM | C36: 1000900 | D36: ER VISIT NO CHARGE. ELOPEMENT | E36: ER VISIT NO CHARGE. ELOPEMENT | F36: **N/A** | G36: 0 | H36: 42552 | O36: 450
A37: 4010 | B37: EMERGENCY ROOM | C37: 1001000 | D37: CLASS 6 CRITICAL CARE 30-74MIN | E37: CLASS 6 CRITICAL CARE 30-74 MINUTES | F37: **N/A** | G37: 5927 | H37: 44197 | I37: 99291 | J37: 25 | M37: Z7502 | O37: 450
A38: 4010 | B38: EMERGENCY ROOM | C38: 1001001 | D38: CRITICAL CARE EACH ADD 30 MIN | E38: CRITICAL CARE EACH ADD 30 MIN | F38: **N/A** | G38: 2306 | H38: 44197 | I38: 99292 | J38: 25 | M38: Z7502 | O38: 450
A39: 4010 | B39: EMERGENCY ROOM | C39: 1001002 | D39: TRAUMA CODE ACTIVATION | E39: TRAUMA CODE ACTIVATION | F39: **N/A** | G39: 6260 | H39: 44197 | I39: G0390 | O39: 684 | Q39: 450
A40: 4470 | B40: MEDICAL SUPPLIES SOLD TO PATIENTS | C40: 1001300 | D40: OXYGEN | E40: OXYGEN | F40: **N/A** | G40: 58 | H40: 42553 | M40: Z7610 | O40: 270
A41: 4391 | B41: OUTPATIENT TREATMENT CENTER | C41: 1001701 | D41: IV INF ADD HR THER/PROF/DIAG | E41: IV INF ADD HR THER/PROF/DIAG | F41: **N/A** | G41: 254 | H41: 44197 | I41: 96366 | M41: 96366 | O41: 260
A42: 4391 | B42: OUTPATIENT TREATMENT CENTER | C42: 1001702 | D42: IV INF SEQ THER/PROF/DIAG | E42: IV INF SEQ THER/PROF/DIAG | F42: **N/A** | G42: 292 | H42: 44197 | I42: 96367 | M42: 96367 | O42: 260
A43: 4391 | B43: OUTPATIENT TREATMENT CENTER | C43: 1001703 | D43: HYDRATE IV INF INITIAL HOUR | E43: HYDRATE IV INF INITIAL HOUR | F43: **N/A** | G43: 532 | H43: 44197 | I43: 96360 | M43: 96360 | O43: 260
A44: 4391 | B44: OUTPATIENT TREATMENT CENTER | C44: 1001705 | D44: IV INF CONCURRENT THER/PROF/DI | E44: IV INF CONCURRENT THER/PROF/DI | F44: **N/A** | G44: 279 | H44: 44197 | I44: 96368 | M44: 96368 | O44: 260
A45: 4391 | B45: OUTPATIENT TREATMENT CENTER | C45: 1001706 | D45: HYDRATE IV INF ADD HOUR | E45: HYDRATE IV INF ADD HOUR | F45: **N/A** | G45: 252 | H45: 44197 | I45: 96361 | M45: 96361 | O45: 260
A46: 4391 | B46: OUTPATIENT TREATMENT CENTER | C46: 1001708 | D46: PHLEBOTOMY THERAPEUTIC | E46: PHLEBOTOMY THERAPEUTIC | F46: **N/A** | G46: 389 | H46: 44197 | I46: 99195 | O46: 761
A47: 4391 | B47: OUTPATIENT TREATMENT CENTER | C47: 1001709 | D47: IV PUSH SEQ SAME DRUG AFTR 30M | E47: IV PUSH SEQ SAME DRUG AFTR 30M | F47: **N/A** | G47: 279 | H47: 44197 | I47: 96376 | O47: 260
A48: 4010 | B48: EMERGENCY ROOM | C48: 1001901 | D48: ER NON CHARGEABLE SUPPLIES,NCH | E48: ER NON CHARGEABLE SUPPLIES,NCH | F48: **N/A** | G48: 0 | H48: 42552 | O48: 270
A49: 4010 | B49: EMERGENCY ROOM | C49: 1001902 | D49: ER NO CHG. LAB CHG. | E49: ER NO CHG. LAB CHG. | F49: **N/A** | G49: 0 | H49: 42552 | O49: 450
A50: 4010 | B50: EMERGENCY ROOM | C50: 1001903 | D50: ER NO CHG. IV INSERTION | E50: ER NO CHG. IV INSERTION. | F50: **N/A** | G50: 0 | H50: 42552 | I50: 36000 | O50: 450
A51: 4010 | B51: EMERGENCY ROOM | C51: 1001904 | D51: ER NO CHG. BLOOD GASES | E51: ER NO CHG. BLOOD GASES | F51: **N/A** | G51: 0 | H51: 42552 | I51: 36600 | O51: 450
A52: 4010 | B52: EMERGENCY ROOM | C52: 1001905 | D52: ER NO CHG. RT CHG CPR | E52: ER NO CHG. RT CHG CPR | F52: **N/A** | G52: 0 | H52: 42552 | O52: 450
A53: 4010 | B53: EMERGENCY ROOM | C53: 1001906 | D53: ER NO CHG. PROCEDURE EKG CHG | E53: ER NO CHG. PROCEDURE EKG CHG | F53: **N/A** | G53: 0 | H53: 42552 | O53: 450
A54: 4010 | B54: EMERGENCY ROOM | C54: 1001907 | D54: ER NO CHG. PULSE OXIMETRY | E54: ER NO CHG. PULSE OXIMETRY | F54: **N/A** | G54: 0 | H54: 42552 | O54: 450
A55: 4010 | B55: EMERGENCY ROOM | C55: 1001908 | D55: ER NO CHG. EPISTAXIS ANT SIMP | E55: ER NO CHG. EPISTAXIS SIMPLE | F55: **N/A** | G55: 0 | H55: 42552 | I55: 30901 | O55: 450
A56: 4010 | B56: EMERGENCY ROOM | C56: 1001909 | D56: ER NO CHG. SKIN CLOSURE | E56: ER NO CHG. SKIN CLOSURE | F56: **N/A** | G56: 0 | H56: 42552 | I56: G0168 | O56: 450
A57: 4010 | B57: EMERGENCY ROOM | C57: 1001910 | D57: ER NO CHG. GAIT TRAINING | E57: ER NO CHG. GAIT TRAINING | F57: **N/A** | G57: 0 | H57: 42552 | O57: 450
A58: 4010 | B58: EMERGENCY ROOM | C58: 1001911 | D58: ER NO CHG. EYE EXAM | E58: ER NO CHG. EYE EXAM | F58: **N/A** | G58: 0 | H58: 42552 | I58: 92002 | O58: 450
A59: 4010 | B59: EMERGENCY ROOM | C59: 1001912 | D59: CPR BY ER STAFF ONLY | E59: CPR BY ER STAFF ONLY | F59: **N/A** | G59: 1770 | H59: 44197 | I59: 92950 | O59: 450
A60: 4010 | B60: EMERGENCY ROOM | C60: 1002500 | D60: INJ SUBCUTANEOUS/INTRAMUSCULAR | E60: INJ SUBCUTANEOUS OR INTRAMUSCULAR | F60: **N/A** | G60: 229 | H60: 44197 | I60: 96372 | M60: 96372 | O60: 450
A61: 4010 | B61: EMERGENCY ROOM | C61: 1002600 | D61: INJ IV PUSH INITIAL | E61: INJ IV PUSH INITIAL | F61: **N/A** | G61: 310 | H61: 44197 | I61: 96374 | M61: 96374 | O61: 450
A62: 4010 | B62: EMERGENCY ROOM | C62: 1002800 | D62: IMMUN ADMIN ONE VACCINE | E62: IMMUNIZTION ADMINISTRATION ONE VACCINE | F62: **N/A** | G62: 105 | H62: 44197 | I62: 90471 | M62: 90471 | O62: 771
A63: 4010 | B63: EMERGENCY ROOM | C63: 1002801 | D63: IMMUN ADMIN VACCINE EACH ADD | E63: IMMUN ADMIN VACCINE EACH ADD | F63: **N/A** | G63: 66 | H63: 44197 | I63: 90472 | O63: 771
A64: 4010 | B64: EMERGENCY ROOM | C64: 1003000 | D64: IV INF INIT HR THER/PROF/DIAG | E64: IV INF INITIAL HR THER/PROF/DIAG | F64: **N/A** | G64: 638 | H64: 44197 | I64: 96365 | M64: 96365 | O64: 450
A65: 4010 | B65: EMERGENCY ROOM | C65: 1003001 | D65: IV INF ADD HR THER/PROF/DIAG | E65: IV INF ADD HR THER/PROF/DIAG | F65: **N/A** | G65: 254 | H65: 44197 | I65: 96366 | M65: 96366 | O65: 450
A66: 4010 | B66: EMERGENCY ROOM | C66: 1003002 | D66: IV INF SEQ THER/PROF/DIAG | E66: IV INF SEQ THER/PROF/DIAG | F66: **N/A** | G66: 292 | H66: 44197 | I66: 96367 | M66: 96367 | O66: 450
A67: 4010 | B67: EMERGENCY ROOM | C67: 1003003 | D67: HYDRATE IV INF INITIAL HOUR | E67: HYDRATE IV INF INITIAL HOUR | F67: **N/A** | G67: 532 | H67: 44197 | I67: 96360 | M67: 96360 | O67: 450
A68: 4010 | B68: EMERGENCY ROOM | C68: 1003004 | D68: HYDRATE IV INF ADD HOUR | E68: HYDRATE IV INF ADD HOUR | F68: **N/A** | G68: 252 | H68: 44197 | I68: 96361 | M68: 96361 | O68: 450
A69: 4010 | B69: EMERGENCY ROOM | C69: 1003006 | D69: IV INF CONCURRENT THER/PROF/DI | E69: IV INF CONCURRENT THER/PROF/DI | F69: **N/A** | G69: 279 | H69: 44197 | I69: 96368 | M69: 96368 | O69: 450
A70: 4010 | B70: EMERGENCY ROOM | C70: 1003008 | D70: CASIRIVI AND IMDEVI INFUSION AND POST MONITORING | E70: CASIRIVI AND IMDEVI INFUSION AND POST MONITORING | F70: **N/A** | G70: 774 | H70: 44166 | I70: M0243 | O70: 771
A71: 4010 | B71: EMERGENCY ROOM | C71: 1003009 | D71: INTRAVENOUS INFUSION, BAMLANIVIMAB AND ETESEVIMAB | E71: INTRAVENOUS INFUSION, BAMLANIVIMAB AND ETESEVIMAB | F71: 774 | G71: 774 | H71: 44273 | I71: M0245 | O71: 771
A72: 4010 | B72: EMERGENCY ROOM | C72: 1003010 | D72: ADMIN SOTROVIMAB INFUSION | E72: ADMIN SOTROVIMAB INFUSION | F72: **N/A** | G72: 774 | H72: 44529 | I72: M0247 | O72: 771
A73: 4010 | B73: EMERGENCY ROOM | C73: 1003011 | D73: BEBTELOVIMAB ADMINISTRATION | E73: BEBTELOVIMAB ADMINISTRATION | F73: **N/A** | G73: 774 | H73: 44649 | I73: M0222 | O73: 771
A74: 4010 | B74: EMERGENCY ROOM | C74: 1003100 | D74: MODERATE SED 1ST 30 MIN | E74: MODERATE SEDATION 1ST 30 MIN | F74: **N/A** | G74: 639 | H74: 42917 | O74: 370
A75: 4010 | B75: EMERGENCY ROOM | C75: 1003101 | D75: MODERATE SEDATION ADD 15 MIN | E75: MODERATE SEDATION ADD 15 MIN | F75: **N/A** | G75: 310 | H75: 42917 | O75: 370
A76: 4010 | B76: EMERGENCY ROOM | C76: 1003500 | D76: ER PROCEDURE 15 MIN | E76: ER PROCEDURE 15 MIN | F76: **N/A** | G76: 492 | H76: 42917 | O76: 459
A77: 4010 | B77: EMERGENCY ROOM | C77: 1003800 | D77: ADMIN INFLUENZA VACCINE | E77: ADMIN INFLUENZA VACCINE | F77: **N/A** | G77: 88 | H77: 44197 | I77: G0008 | O77: 771
A78: 4010 | B78: EMERGENCY ROOM | C78: 1003900 | D78: ADMIN PNEUMOCOCCAL VACCINE | E78: ADMIN PNEUMOCOCCAL VACCINE | F78: **N/A** | G78: 88 | H78: 44197 | I78: G0009 | O78: 771
A79: 4010 | B79: EMERGENCY ROOM | C79: 1003901 | D79: ADMIN HEPATITIS B VACCINE | E79: ADMIN HEPATITIS B VACCINE | F79: **N/A** | G79: 88 | H79: 44197 | I79: G0010 | O79: 771
A80: 4010 | B80: EMERGENCY ROOM | C80: 1004000 | D80: URINE MULTI-STICK EACH | E80: URINE MULTI-STICK EACH | F80: **N/A** | G80: 68 | H80: 44197 | I80: 81003 | M80: Z7610 | O80: 300
A81: 4010 | B81: EMERGENCY ROOM | C81: 1004100 | D81: IV PUSH SEQUENTIAL DIFF DRUG | E81: IV PUSH SEQUENTIAL DIFFERENT DRUG | F81: **N/A** | G81: 272 | H81: 44197 | I81: 96375 | M81: 96375 | O81: 450
A82: 4010 | B82: EMERGENCY ROOM | C82: 1004101 | D82: IV PUSH SEQ SAME DRUG AFTR 30M | E82: IVPUSH SEQ SAME DRUG AFTER 30M | F82: **N/A** | G82: 279 | H82: 44197 | I82: 96376 | M82: 96376 | O82: 450
A83: 4010 | B83: EMERGENCY ROOM | C83: 1004700 | D83: INJ S/C OR IM SEP PROCEDURE | E83: INJECTION SUB Q OR IM SEPARATE PROCEDURE | F83: **N/A** | G83: 229 | H83: 44197 | I83: 96372 | M83: 96372 | O83: 450
A84: 4010 | B84: EMERGENCY ROOM | C84: 1004800 | D84: ULTRASOUND,BLADDER CAPACITY | E84: ULTRASOUND,BLADDER CAPACITY | F84: **N/A** | G84: 193 | H84: 44197 | I84: 51798 | O84: 450
A85: 4010 | B85: EMERGENCY ROOM | C85: 1004811 | D85: ER PROCEDURE I | E85: ER PROCEDURE I | F85: **N/A** | G85: 221 | H85: 42553 | O85: 459
A86: 4010 | B86: EMERGENCY ROOM | C86: 1004812 | D86: ER PROCEDURE II | E86: ER PROCEDURE II | F86: **N/A** | G86: 488 | H86: 42553 | O86: 459
A87: 4010 | B87: EMERGENCY ROOM | C87: 1004813 | D87: ER PROC III | E87: ER PROC III | F87: **N/A** | G87: 1352 | H87: 42553 | O87: 459
A88: 4010 | B88: EMERGENCY ROOM | C88: 1004814 | D88: ER PROC IV | E88: ER PROCEDURE IV | F88: **N/A** | G88: 1856 | H88: 42553 | O88: 459
A89: 4010 | B89: EMERGENCY ROOM | C89: 1004815 | D89: ER PROCEDURE V | E89: ER PROCEDURE V | F89: **N/A** | G89: 2834 | H89: 42553 | O89: 459
A90: 4010 | B90: EMERGENCY ROOM | C90: 1004900 | D90: POCUS US ABDOMINAL REAL TIME W/IMAGE | E90: US ABDOMINAL REAL TIME W/IMAGE | F90: **N/A** | G90: 915 | H90: 44197 | I90: 76705 | J90: 52 | M90: 76705 | N90: TC 52 | O90: 320
A91: 4010 | B91: EMERGENCY ROOM | C91: 1004901 | D91: POCUS ECHO TRANSTHORC R-T 2D W/WO M-MODE REC F-UP | E91: ECHO TRANSTHORC R-T 2D W/WO M-MODE REC F-UP | F91: **N/A** | G91: 848 | H91: 44197 | I91: 93308 | O91: 480
A92: 4010 | B92: EMERGENCY ROOM | C92: 1004902 | D92: POCUS US CHEST REAL TIME W/ IMAGE DOCUMENTATION | E92: US CHEST REAL TIME W/ IMAGE DOCUMENTATION | F92: **N/A** | G92: 933 | H92: 44197 | I92: 76604 | M92: 76604 | N92: TC | O92: 402
A93: 4010 | B93: EMERGENCY ROOM | C93: 1004903 | D93: POCUS ULTRASOUND OB/GYN LIMIT | E93: ULTRASOUND OB/GYN PELVIS LIMIT | F93: **N/A** | G93: 535 | H93: 44197 | I93: 76815 | J93: 52 | M93: 76815 | N93: 52 TC | O93: 402
A94: 4010 | B94: EMERGENCY ROOM | C94: 1004904 | D94: POCUS ULTRASOUND RETROPERITON LIMIT | E94: ULTRASOUND RETROPERITON LIMIT | F94: **N/A** | G94: 1020 | H94: 44197 | I94: 76775 | M94: 76775 | N94: TC | O94: 402
A95: 4010 | B95: EMERGENCY ROOM | C95: 1004905 | D95: POCUS ULTRASOUND PELVIS LIMITED | E95: ULTRASOUND PELVIS LIMITED | F95: **N/A** | G95: 688 | H95: 44197 | I95: 76857 | M95: 76857 | N95: TC | O95: 402
A96: 4010 | B96: EMERGENCY ROOM | C96: 1004906 | D96: POCUS ULTRASOUND VEINS UNILAT DUPLEX | E96: ULTRASOUND VEINS UNILAT DUPLEX | F96: **N/A** | G96: 1481 | H96: 44197 | I96: 93971 | M96: 93971 | N96: TC | O96: 921 | Q96: 402
A97: 4010 | B97: EMERGENCY ROOM | C97: 1004907 | D97: POCUS US EXTREMITY LIMITED | E97: US EXTREMITY LIMITED | F97: **N/A** | G97: 1347 | H97: 44197 | I97: 76882 | M97: 76882 | N97: TC | O97: 402
A98: 4010 | B98: EMERGENCY ROOM | C98: 1004908 | D98: POCUS OCULAR | E98: POCUS OCULAR | F98: **N/A** | G98: 445 | H98: 44197 | I98: 76512 | M98: 76512 | N98: TC | O98: 402
A99: 4010 | B99: EMERGENCY ROOM | C99: 1004909 | D99: POCUS PERICARDIOCENTESIS US GUIDE | E99: PERICARDIOCENTESIS US GUIDE | F99: **N/A** | G99: 588 | H99: 42916 | I99: 76930 | M99: 76930 | N99: TC | O99: 402
A100: 4010 | B100: EMERGENCY ROOM | C100: 1004910 | D100: POCUS US GUIDED VASCULAR ACCESS | E100: US GUIDED VASCULAR ACCESS | F100: **N/A** | G100: 1170 | H100: 44197 | I100: 76937 | M100: 76937 | N100: TC | O100: 402
A101: 4010 | B101: EMERGENCY ROOM | C101: 1004911 | D101: POCUS US GUIDANCE NEEDLE PLACEMENT | E101: US GUIDANCE NEEDLE PLACEMENT | F101: **N/A** | G101: 1340 | H101: 44197 | I101: 76942 | M101: 76942 | N101: TC | O101: 402
...
